yt_dlp_plugins/extractor/yt_dlp_get_pot_rustypipe.py
yt_dlp_get_pot_rustypipe-0.2.0.dist-info/METADATA
yt_dlp_get_pot_rustypipe-0.2.0.dist-info/WHEEL
yt_dlp_get_pot_rustypipe-0.2.0.dist-info/RECORD
