Metadata-Version: 2.4
Name: yt-dlp-get-pot-rustypipe
Version: 0.2.0
Summary: yt-dlp plugin for fetching PO tokens using rustypipe-botguard
Maintainer-email: ThetaDev <thetadev@magenta.de>
License-Expression: MIT
Keywords: yt-dlp,yt-dlp-plugin,yt-dlp-plugins-get-pot
Classifier: License :: OSI Approved :: MIT License
Requires-Python: >=3.9
Requires-Dist: yt-dlp>=2025.05.22
